Samanvay_Sdk/__init__.py
Samanvay_Sdk/client.py
samanvay_sdk-0.0.1.dist-info/METADATA
samanvay_sdk-0.0.1.dist-info/WHEEL
samanvay_sdk-0.0.1.dist-info/top_level.txt
samanvay_sdk-0.0.1.dist-info/RECORD
