Metadata-Version: 2.4
Name: samanvay-sdk
Version: 0.0.1
Summary: Python SDK for accessing Samanvay Kumar Tadakamalla's professional profile
Author-email: Samanvay Kumar Tadakamalla <s.tadakamalla@theshiftai.in>
Project-URL: Repository, https://github.com/samanvay-kumar/Samanvay-sdk
Project-URL: LinkedIn, https://www.linkedin.com/in/samanvay-kumar-tadakamalla
Requires-Python: >=3.8
